{
  "tasks": [
    {
      "date": "2021-12-15",
      "dueDate": "2021-12-15",
      "description": "Teeeest",
      "done": false,
      "id": "1vZjBem"
    },
    {
      "date": "2021-12-15",
      "dueDate": "2021-12-17",
      "description": "sqd",
      "done": false,
      "id": "MBRC330"
    },
    {
      "date": "2021-12-15",
      "dueDate": "2021-12-18",
      "description": "fghfghfgh",
      "done": false,
      "id": "J4ok2f5"
    },
    {
      "date": "2021-12-15",
      "dueDate": "2021-12-29",
      "description": "ggggg",
      "done": false,
      "id": "0XAMtKn"
    },
    {
      "date": "2021-12-15",
      "dueDate": "2021-12-29",
      "description": "fdgdgfdfdf",
      "done": false,
      "id": "RIfJFXW"
    },
    {
      "date": "2021-12-15",
      "dueDate": "2021-12-15",
      "description": "fghhgfh",
      "done": false,
      "id": "Xmdq0p0"
    },
    {
      "date": "2021-12-15",
      "dueDate": "2021-12-15",
      "description": "tryrty",
      "done": false,
      "id": "ji8pV2v"
    },
    {
      "date": "2021-12-15",
      "dueDate": "2021-12-15",
      "description": "ffff",
      "done": false,
      "id": "twCgoVd"
    },
    {
      "date": "2021-12-15",
      "dueDate": "2021-12-15",
      "description": "hfhgffhfh",
      "done": false,
      "id": "i192O2b"
    },
    {
      "date": "2021-12-15",
      "dueDate": "2021-12-15",
      "description": "vbnvb",
      "done": false,
      "id": "qLJkNoL"
    },
    {
      "date": "2021-12-15",
      "dueDate": "2021-12-30",
      "description": "hhhhh",
      "done": false,
      "id": "JXKdG9p"
    }
  ]
}